Metadata-Version: 1.0
Name: AWS-Matope-Sithole-distributions
Version: 0.1
Summary: Gaussian and Binomial distributions
Home-page: UNKNOWN
Author: Matope Sithole
Author-email: matopesithole@gmail.com
License: UNKNOWN
Platform: UNKNOWN
